{
  "/api/consultants/route": "app/api/consultants/route.js",
  "/api/auth/route": "app/api/auth/route.js",
  "/api/admin/route": "app/api/admin/route.js",
  "/api/documents/route": "app/api/documents/route.js",
  "/api/notifications/preferences/route": "app/api/notifications/preferences/route.js",
  "/_not-found/page": "app/_not-found/page.js",
  "/api/notifications/session/route": "app/api/notifications/session/route.js",
  "/api/notifications/route": "app/api/notifications/route.js",
  "/api/progress/route": "app/api/progress/route.js",
  "/api/scheduling/route": "app/api/scheduling/route.js",
  "/api/students/[id]/sessions/route": "app/api/students/[id]/sessions/route.js",
  "/api/students/[id]/progress/route": "app/api/students/[id]/progress/route.js",
  "/api/test-db/route": "app/api/test-db/route.js",
  "/api/students/route": "app/api/students/route.js",
  "/api/test/route": "app/api/test/route.js",
  "/api/video/route": "app/api/video/route.js",
  "/auth/login/page": "app/auth/login/page.js",
  "/auth/register/page": "app/auth/register/page.js",
  "/dashboard/consultant/page": "app/dashboard/consultant/page.js",
  "/dashboard/documents/page": "app/dashboard/documents/page.js",
  "/dashboard/student/page": "app/dashboard/student/page.js",
  "/page": "app/page.js",
  "/dashboard/progress/page": "app/dashboard/progress/page.js",
  "/settings/notifications/page": "app/settings/notifications/page.js",
  "/test/page": "app/test/page.js",
  "/scheduling/page": "app/scheduling/page.js",
  "/test-simple/page": "app/test-simple/page.js",
  "/video/session/[sessionId]/page": "app/video/session/[sessionId]/page.js"
}